{
  "cardsdesc" : {
    "3" : {
      "box" : "core",
      "faction" : "GARREKREAVERS",
      "fluff" : "The retreat is weakness, and the weak must be culled.",
      "name" : "Coward!",
      "rule" : "Score this immediately if an enemy fighter begins a Move action adjacent to one of your fighters and ends it adjacent to none of your fighters.",
      "rule34" : "",
      "score" : "1",
      "subtype" : "",
      "type" : "OBJECTIVE"
    },
    "4" : {
      "box" : "core",
      "faction" : "GARREKREAVERS",
      "fluff" : "The Blood God marks well the names of those who commit great acts of slaughter in his name.",
      "name" : "Draw The Gaze Of Khorne",
      "rule" : "Score this immediately if your warband takes two or more enemy fighters out of action in this phase.",
      "rule34" : "",
      "score" : "1",
      "subtype" : "",
      "type" : "OBJECTIVE"
    },
    "7" : {
      "box" : "core",
      "faction" : "GARREKREAVERS",
      "fluff" : "The weak fall, and only the mighty are left standing. Such is the will of Khorne.",
      "name" : "Khorne's Champion",
      "rule" : "Score this in the third end phase if all the fighters except one of your fighters are out of action",
      "rule34" : "",
      "score" : "6",
      "subtype" : "",
      "type" : "OBJECTIVE"
    },
    "8" : {
      "box" : "core",
      "faction" : "GARREKREAVERS",
      "fluff" : "All must wet their blade with the blood of the foe. To fail in this task is to invite the Blood God's wrath.",
      "name" : "Let The Blood Flow",
      "rule" : "Score this immediately if three or more of your fighters made a successful Attack action in this phase.",
      "rule34" : "",
      "score" : "2",
      "subtype" : "",
      "type" : "OBJECTIVE"
    },
    "18" : {
      "box" : "core",
      "faction" : "GARREKREAVERS",
      "fluff" : "The blood is death. The blood is life. The blood must flow.",
      "name" : "Rebirth In Blood",
      "rule" : "Reaction: Play this after an Attack action or ploy that takes your last surviving fighter out of action. Roll a defence dice. If you roll SHIELD or CRITICAL remove all wound tokens from them, and place them on starting hex in your territory.",
      "subtype" : "PLOY",
      "type" : "POWER"
    },
    "23" : {
      "box" : "core",
      "faction" : "GARREKREAVERS",
      "fluff" : "That's a pretty face. I think I'll flay it and hang from it from my belt. - Garrek Gorebeard",
      "name" : "Ever-Advancing",
      "restriction" : "GARREK",
      "rule" : "When this fighter takes an enemy fighter out of action, gain 1 additional glory point.",
      "subtype" : "UPGRADE",
      "type" : "POWER"
    },
    "25" : {
      "box" : "core",
      "faction" : "GARREKREAVERS",
      "fluff" : "That's a pretty face. I think I'll flay it and hang from it from my belt. - Garrek Gorebeard",
      "name" : "Grisly Trophy",
      "restriction" : "GARREK",
      "rule" : "When this fighter takes an enemy fighter out of action, gain 1 additional glory point.",
      "subtype" : "UPGRADE",
      "type" : "POWER"
    },
    "26" : {
      "box" : "core",
      "faction" : "GARREKREAVERS",
      "fluff" : "Karsus' frenzied screams of battle-lust are enough to shake the will of even the sturdiest foe.",
      "name" : "Terrifying Howl",
      "restriction" : "KARSUS",
      "rule" : "Action: Push each adjacent enemy fighter one hex.",
      "subtype" : "UPGRADE",
      "type" : "POWER"
    },
    "31" : {
      "box" : "core",
      "faction" : "STEELHEARTLIBERATORS",
      "fluff" : "All manner of corrupt and malicious souls haunt the shadowed streets of Shadespire. They shall all fall before the might of Sigmar.",
      "name" : "Cleanse",
      "rule" : "Score this in an end phase if you hold all the objectives in enemy territory.",
      "rule34" : "in any one of your enemies' territories.",
      "score" : "3",
      "subtype" : "",
      "type" : "OBJECTIVE"
    },
    "32" : {
      "box" : "core",
      "faction" : "STEELHEARTLIBERATORS",
      "fluff" : "This is hallowed land, heathen. Take one step further and feel the wrath of Sigmar.",
      "name" : "Consecrated Area",
      "rule" : "Score this in an end phase if there are no enemy fighters adjacent to your fighters.",
      "rule34" : "",
      "score" : "1",
      "subtype" : "",
      "type" : "OBJECTIVE"
    },
    "34" : {
      "box" : "core",
      "faction" : "STEELHEARTLIBERATORS",
      "fluff" : "I claim this shard in the name of the God King. Flee, while you still have use of your limbs. - Angharad Brightshield.",
      "name" : "Immovable Object",
      "rule" : "Score this in an end phase if the same friendly fighter has held the same objective at the end of two consecutive action phases.",
      "rule34" : "",
      "score" : "1",
      "subtype" : "",
      "type" : "OBJECTIVE"
    },
    "36" : {
      "box" : "core",
      "faction" : "STEELHEARTLIBERATORS",
      "fluff" : "Steelheart's band have sworn to end the curse of Shadespire and escape their nightmarish prison. Woe to those who stand in their way.",
      "name" : "Seize Ground",
      "rule" : "Score this in an end phase if you hold an objective in enemy territory.",
      "rule34" : "",
      "score" : "1",
      "subtype" : "",
      "type" : "OBJECTIVE"
    },
    "45" : {
      "box" : "core",
      "faction" : "STEELHEARTLIBERATORS",
      "fluff" : "Fear not, heathen. I can keep this up all day.",
      "name" : "Tireless Assault",
      "rule" : "Reaction: Play this after a friendly fighter's Attack action that fails. That fighter can make another Attack action that targets the same fighter.",
      "subtype" : "PLOY",
      "type" : "POWER"
    },
    "49" : {
      "box" : "core",
      "faction" : "STEELHEARTLIBERATORS",
      "fluff" : "'We shall not fall here. Sigmar's light will guide us home.' - Severin Steelheart",
      "name" : "Blessed By Sigmar",
      "rule" : "+1 Wounds",
      "subtype" : "UPGRADE",
      "type" : "POWER"
    },
    "52" : {
      "box" : "core",
      "faction" : "STEELHEARTLIBERATORS",
      "fluff" : "Even amongst his warrior kin, Steelheart's skill with the blade is the stuff of legend.",
      "name" : "Fatal Riposte",
      "restriction" : "STEELHEART",
      "rule" : "Reaction: During an Attack action that targets this fighter and fails, roll an attack dice. On a roll of HAMMER or CRITICAL this fighter cannot be driven back and they can make an Attack action. It must target the attacker.",
      "subtype" : "UPGRADE",
      "type" : "POWER"
    },
    "54" : {
      "box" : "core",
      "faction" : "STEELHEARTLIBERATORS",
      "fluff" : "A well-timed countercharge can turn the tide of battle in an instant.",
      "name" : "Heroic Stride",
      "restriction" : "STEELHEART",
      "rule" : "Reaction: After an enemy fighter ends their activation within two hexes of this fighter, you can push this fighter one hex.",
      "subtype" : "UPGRADE",
      "type" : "POWER"
    }
  },
  "cardslist" : {
    "1" : "A Worthy Skull",
    "2" : "Blood For The Blood God!",
    "3" : "Coward!",
    "4" : "Draw The Gaze Of Khorne",
    "5" : "It Begins",
    "6" : "Khorne Cares Not",
    "7" : "Khorne's Champion",
    "8" : "Let The Blood Flow",
    "9" : "There Is Only Slaughter",
    "10" : "Blood Offering",
    "11" : "Blood Rain",
    "12" : "Boon Of Khorne",
    "13" : "Desecrate",
    "14" : "Final Blow",
    "15" : "Fuelled By Slaughter",
    "16" : "Insensate",
    "17" : "Khorne Calls",
    "18" : "Rebirth In Blood",
    "19" : "Skulls For The Skull Throne!",
    "20" : "Berserk Charge",
    "21" : "Bloodslick",
    "22" : "Deadly Spin",
    "23" : "Ever-Advancing",
    "24" : "Frenzy",
    "25" : "Grisly Trophy",
    "26" : "Terrifying Howl",
    "27" : "Unstoppable Charge",
    "28" : "Whirlwind of Death",
    "29" : "Wicked Blade",
    "30" : "Awe-Inspiring",
    "31" : "Cleanse",
    "32" : "Consecrated Area",
    "33" : "Eternals",
    "34" : "Immovable Object",
    "35" : "Lightning Strikes",
    "36" : "Seize Ground",
    "37" : "Sigmar's Bulwark",
    "38" : "Slayers Of Tyrants",
    "39" : "Heroic Guard",
    "40" : "Peal Of Thunder",
    "41" : "Righteous Zeal",
    "42" : "Sigmarite Wall",
    "43" : "Stormforged Resistance",
    "44" : "Stormforged Tactics",
    "45" : "Tireless Assault",
    "46" : "Undaunted",
    "47" : "Unstoppable Strike",
    "48" : "Valiant Attack",
    "49" : "Blessed by Sigmar",
    "50" : "Block",
    "51" : "Brave Strike",
    "52" : "Fatal Riposte",
    "53" : "Heroic Might",
    "54" : "Heroic Stride",
    "55" : "Lightning Blade",
    "56" : "Lightning Blast",
    "57" : "Righteous Strike",
    "58" : "Shield Bash",
    "59" : "Battle Without End",
    "60" : "Claim The City",
    "61" : "Fearless In Death",
    "62" : "March Of The Dead",
    "63" : "More Able Bodies",
    "64" : "Peerless General",
    "65" : "Skills Unforgotten",
    "66" : "The Invigorated Dead",
    "67" : "Undead Swarm",
    "68" : "Bone Shrapnel",
    "69" : "Ceaseless Attacks",
    "70" : "Clawing Hands",
    "71" : "Dance Macabre",
    "72" : "Grasping Hands",
    "73" : "Restless Dead",
    "74" : "Spectral Form",
    "75" : "Swift Evasion",
    "76" : "Terrifying Screams",
    "77" : "The Necromancer Commands",
    "78" : "Ancient Commander",
    "79" : "Assumed Command  ",
    "80" : "Deathly Charge",
    "81" : "Fatal Strike",
    "82" : "Focused Attack",
    "83" : "Frightning Speed",
    "84" : "Grim Cleave",
    "85" : "Lethal Lunge",
    "86" : "Remembered Shield",
    "87" : "Undying",
    "88" : "Ard As Iron",
    "89" : "Biggest 'an da Best",
    "90" : "Call Of The Waaagh!",
    "91" : "Dead Kunnin'",
    "92" : "Dere's More Of Us",
    "93" : "Get da Boss",
    "94" : "Good Scrap",
    "95" : "Punch-up",
    "96" : "Too Dumb to Die",
    "97" : "Avin a Good Time",
    "98" : "Brutal but Kunnin'",
    "99" : "Deafening Bellow",
    "100" : "Gorkamorka's Blessing",
    "101" : "Kunnin' but Brutal",
    "102" : "Last Lunge",
    "103" : "Leadin' by Example",
    "104" : "More Choppin'",
    "105" : "Pillage",
    "106" : "Scrag 'Em",
    "107" : "Ard Head",
    "108" : "Aspiring Boss",
    "109" : "Brutal Frenzy",
    "110" : "Brutal Swing",
    "111" : "Crush and Cleave",
    "112" : "Dead 'Ard",
    "113" : "Eadbutt",
    "114" : "Headlong Rush",
    "115" : "Unkillable",
    "116" : "Waaagh!",
    "236" : "Annihilation",
    "239" : "Blooded",
    "240" : "Bloodless",
    "241" : "Brawl",
    "247" : "Conquest",
    "248" : "Contained",
    "250" : "Crushing Force",
    "253" : "Denial",
    "254" : "Determined Defender",
    "255" : "Devide and Conquer",
    "256" : "Endless Slaughter",
    "259" : "Flawless Strategy",
    "260" : "Geared for War",
    "263" : "Hold Objective 1",
    "264" : "Hold Objective 2",
    "265" : "Hold Objective 3",
    "266" : "Hold Objective 4",
    "267" : "Hold Objective 5",
    "281" : "Plant A Standard",
    "282" : "Ploymaster",
    "287" : "Reaper",
    "288" : "Scent of Victory",
    "290" : "Stymied",
    "291" : "Superior Tactician",
    "292" : "Supremacy",
    "293" : "Swift Advance",
    "296" : "Tactical Supremacy 1-2",
    "297" : "Tactical Supremacy 3-4",
    "299" : "The Harvest Begins",
    "302" : "Twilight Conquerer",
    "305" : "Victorious Duel",
    "308" : "Anticipation",
    "311" : "Confusion",
    "312" : "Cruel Taunt",
    "315" : "Daylight Robbery",
    "318" : "Distractions",
    "319" : "Dual Strike",
    "320" : "Duel of Wits",
    "324" : "Forceful Denial",
    "325" : "Fortify",
    "330" : "Healing Potion",
    "332" : "Illusory Fighter",
    "339" : "Mighty Swing",
    "341" : "Misdirection",
    "345" : "On Your Feet",
    "346" : "Parry",
    "353" : "Scavenge",
    "355" : "Shardfall",
    "357" : "Shattering Terrain",
    "359" : "Shiting Shards",
    "360" : "Sidestep",
    "361" : "Stumble",
    "363" : "Sprint",
    "364" : "Stumble",
    "368" : "Time Trap",
    "370" : "Triumphant Roar",
    "371" : "Trust To Luck",
    "381" : "Cursed Artefact",
    "382" : "Daemonic Weapon",
    "385" : "Disengage",
    "387" : "Flickering Image",
    "389" : "Great Fortitude",
    "390" : "Great Speed",
    "391" : "Great Strength",
    "396" : "Katophrane's Belt",
    "402" : "Legendary Swiftness",
    "405" : "Low Blow",
    "411" : "Shadeglass Darts",
    "416" : "Shardcaller",
    "423" : "Swift Strike",
    "430" : "The Shadowed Key",
    "431" : "Total Offence"
  },
  "decks" : [ null, {
    "author" : "Games Workshop",
    "description" : "Starting deck from the Core Box to play with Steelheart's Liberators.",
    "id" : 1,
    "objective" : [ 30, 33, 35, 37, 38, 236, 253, 263, 264, 265, 266, 267 ],
    "power" : [ 39, 40, 41, 43, 45, 47, 48, 50, 51, 53, 55, 56, 57, 58, 311, 330, 360, 389, 390, 391 ],
    "title" : "Liberators Core Box Deck"
  }, {
    "author" : "Games Workshop",
    "description" : "Starting deck from the Core Box to play with Garrek's Bloodreavers.",
    "id" : 2,
    "objective" : [ 1, 2, 5, 6, 9, 236, 247, 263, 264, 265, 266, 267 ],
    "power" : [ 10, 11, 13, 14, 16, 17, 19, 20, 21, 22, 24, 27, 28, 29, 311, 330, 360, 389, 390, 391 ],
    "title" : "Bloodreavers Core Box Deck"
  }, {
    "author" : "Games Workshop",
    "description" : "This is not a real deck, but just some extra cards included in the core box.",
    "id" : 3,
    "objective" : [ 3, 4, 7, 8, 31, 32, 34, 36, 247, 253, 292, 292 ],
    "power" : [ 12, 15, 18, 23, 25, 26, 42, 44, 46, 49, 52, 54, 355, 355, 363, 363, 385, 385, 431, 431 ],
    "title" : "Core Box Extra Cards"
  } ],
  "expansions" : [ {
    "cards" : [ 1, 2, 3, 4, 5, 6, 7, 8, 9, 10, 11, 12, 13, 14, 15, 16, 17, 18, 19, 20, 21, 22, 23, 24, 25, 26, 27, 28, 29, 30, 31, 32, 33, 34, 35, 36, 37, 38, 39, 40, 41, 42, 43, 44, 45, 46, 47, 48, 49, 50, 51, 52, 53, 54, 55, 56, 57, 58, 236, 236, 247, 247, 253, 253, 263, 263, 264, 264, 265, 265, 266, 266, 267, 267, 292, 292, 311, 311, 330, 330, 355, 355, 360, 360, 363, 363, 385, 385, 389, 389, 390, 390, 391, 391, 431, 431 ],
    "title" : "Warhammer Underworlds Shadespire Core Set"
  }, {
    "cards" : [ 59, 60, 61, 62, 63, 64, 65, 66, 67, 68, 69, 70, 71, 72, 73, 74, 75, 76, 77, 78, 79, 80, 81, 82, 83, 84, 85, 86, 87, 240, 250, 254, 259, 281, 287, 290, 293, 296, 297, 299, 324, 325, 332, 339, 353, 357, 364, 368, 370, 371, 375, 377, 379, 380, 393, 401, 414, 418, 420, 426 ],
    "title" : "Sepulchral Guard"
  }, {
    "cards" : [ 88, 89, 90, 91, 92, 93, 94, 95, 96, 97, 98, 99, 100, 101, 102, 103, 104, 105, 106, 107, 108, 109, 110, 111, 112, 113, 114, 115, 116, 239, 241, 248, 255, 256, 260, 282, 288, 291, 302, 305, 308, 312, 315, 318, 319, 320, 341, 345, 346, 359, 361, 381, 382, 387, 396, 402, 405, 411, 416, 423, 430 ],
    "title" : "Ironskull's Boyz"
  } ],
  "fighters" : {
    "angharad" : {
      "attack" : {
        "damage" : 2,
        "distance" : 1,
        "name" : "Sigmarite Hammer",
        "toHit" : 3,
        "toHitIcon" : "HAMMERS"
      },
      "defence" : 1,
      "defenceIcon" : "SHIELD",
      "inspiration" : "The fighter rolls SHIELD or CRITICAL when target of an attack",
      "move" : 3,
      "name" : "Angharad Brightshield",
      "warband" : "Liberators",
      "wounds" : 4
    },
    "angharadinspired" : {
      "attack" : [ {
        "damage" : 2,
        "distance" : 1,
        "name" : "Sigmarite Hammer",
        "toHit" : 3,
        "toHitIcon" : "HAMMERS"
      }, {
        "damage" : 1,
        "distance" : 1,
        "name" : "Furious Parry",
        "rule" : "Reaction: During an attack action that targets this fighter and has failed, this fighter cannot be driven back and you can make this Attack action. It must target the attacker.",
        "toHit" : 2,
        "toHitIcon" : "HAMMERS"
      } ],
      "defence" : 2,
      "defenceIcon" : "SHIELD",
      "move" : 3,
      "name" : "Brightshield Inspired",
      "warband" : "Liberators",
      "wounds" : 4
    },
    "arnulf" : {
      "attack" : {
        "damage" : 1,
        "distance" : 1,
        "name" : "Piercing Blade and Axe",
        "rule" : "On a critical hit, this Attack action deals 1 extra damage.",
        "toHit" : 2,
        "toHitIcon" : "SWORDS"
      },
      "defence" : 1,
      "defenceIcon" : "DODGE",
      "inspiration" : "At least three fighters are out of action",
      "move" : 4,
      "name" : "Arnulf",
      "warband" : "Bloodreavers",
      "wounds" : 2
    },
    "arnulfinspired" : {
      "attack" : {
        "damage" : 1,
        "distance" : 1,
        "name" : "Piercing Blade and Axe",
        "rule" : "On a critical hit, this Attack action deals 1 extra damage.",
        "toHit" : 3,
        "toHitIcon" : "SWORDS"
      },
      "defence" : 1,
      "defenceIcon" : "DODGE",
      "move" : 5,
      "name" : "Arnulf Inspired",
      "warband" : "Bloodreavers",
      "wounds" : 2
    },
    "garrek" : {
      "attack" : {
        "damage" : 2,
        "distance" : 1,
        "name" : "Blooddrinker Axe",
        "toHit" : 2,
        "toHitIcon" : "HAMMERS"
      },
      "defence" : 1,
      "defenceIcon" : "DODGE",
      "inspiration" : "At least three fighters are out of action",
      "move" : 4,
      "name" : "Garrek Gorebeard",
      "warband" : "Bloodreavers",
      "wounds" : 4
    },
    "garrekinspired" : {
      "attack" : {
        "damage" : 3,
        "distance" : 1,
        "name" : "Awakened Axe",
        "toHit" : 2,
        "toHitIcon" : "HAMMERS"
      },
      "defence" : 1,
      "defenceIcon" : "DODGE",
      "move" : 5,
      "name" : "Garrek Inspired",
      "warband" : "Bloodreavers",
      "wounds" : 2
    },
    "karsus" : {
      "attack" : [ {
        "damage" : 1,
        "distance" : 2,
        "name" : "Chained Axe",
        "toHit" : 3,
        "toHitIcon" : "SWORDS"
      }, {
        "damage" : 2,
        "distance" : 1,
        "name" : "Brutal Chop",
        "toHit" : 3,
        "toHitIcon" : "SWORDS"
      } ],
      "defence" : 1,
      "defenceIcon" : "DODGE",
      "inspiration" : "At least three fighters are out of action",
      "move" : 4,
      "name" : "Karsus The Chained",
      "warband" : "Bloodreavers",
      "wounds" : 3
    },
    "karsusinspired" : {
      "attack" : [ {
        "damage" : 2,
        "distance" : 2,
        "name" : "Chained Axe",
        "toHit" : 3,
        "toHitIcon" : "SWORDS"
      }, {
        "damage" : 2,
        "distance" : 1,
        "name" : "Savage Whirl",
        "rule" : "Targets all adjacent enemies - roll for each.",
        "toHit" : 2,
        "toHitIcon" : "SWORDS"
      } ],
      "defence" : 1,
      "defenceIcon" : "DODGE",
      "move" : 5,
      "name" : "Saek Inspired",
      "warband" : "Bloodreavers",
      "wounds" : 3
    },
    "obryn" : {
      "attack" : {
        "damage" : 3,
        "distance" : 1,
        "extra" : "KNOCKBACK 1",
        "name" : "Sigmarite Grandhammer",
        "toHit" : 2,
        "toHitIcon" : "HAMMERS"
      },
      "defence" : 1,
      "defenceIcon" : "SHIELD",
      "inspiration" : "The fighter rolls SHIELD or CRITICAL when target of an attack",
      "move" : 3,
      "name" : "Obryn The Bold",
      "warband" : "Liberators",
      "wounds" : 4
    },
    "obryninspired" : {
      "attack" : [ {
        "damage" : 3,
        "distance" : 1,
        "extra" : "KNOCKBACK 1",
        "name" : "Sigmarite Grandhammer",
        "toHit" : 2,
        "toHitIcon" : "HAMMERS"
      }, {
        "damage" : 3,
        "distance" : 1,
        "extra" : "CLEAVE",
        "name" : "Overhead Strike",
        "toHit" : 2,
        "toHitIcon" : "HAMMERS"
      } ],
      "defence" : 2,
      "defenceIcon" : "SHIELD",
      "move" : 3,
      "name" : "Obryn Inspired",
      "warband" : "Liberators",
      "wounds" : 4
    },
    "saek" : {
      "attack" : {
        "damage" : 3,
        "distance" : 1,
        "name" : "Great Axe",
        "toHit" : 2,
        "toHitIcon" : "HAMMERS"
      },
      "defence" : 1,
      "defenceIcon" : "DODGE",
      "inspiration" : "At least three fighters are out of action",
      "move" : 4,
      "name" : "Blooded Saek",
      "warband" : "Bloodreavers",
      "wounds" : 3
    },
    "saekinspired" : {
      "attack" : {
        "damage" : 3,
        "distance" : 1,
        "extra" : "CLEAVE",
        "name" : "Great Axe",
        "toHit" : 2,
        "toHitIcon" : "HAMMERS"
      },
      "defence" : 1,
      "defenceIcon" : "DODGE",
      "move" : 5,
      "name" : "Saek Inspired",
      "warband" : "Bloodreavers",
      "wounds" : 3
    },
    "severin" : {
      "attack" : {
        "damage" : 3,
        "distance" : 1,
        "name" : "Sigmarite Broadsword",
        "toHit" : 2,
        "toHitIcon" : "HAMMERS"
      },
      "defence" : 1,
      "defenceIcon" : "SHIELD",
      "inspiration" : "The fighter rolls SHIELD or CRITICAL when target of an attack",
      "move" : 3,
      "name" : "Severin Steelheart",
      "warband" : "Liberators",
      "wounds" : 4
    },
    "severininspired" : {
      "attack" : [ {
        "damage" : 3,
        "distance" : 1,
        "name" : "Sigmarite Broadsword",
        "toHit" : 2,
        "toHitIcon" : "HAMMERS"
      }, {
        "damage" : 2,
        "distance" : 1,
        "name" : "Mighty Swing",
        "rule" : "Targets all adjacent enemies - roll for each.",
        "toHit" : 2,
        "toHitIcon" : "HAMMERS"
      } ],
      "defence" : 2,
      "defenceIcon" : "SHIELD",
      "move" : 3,
      "name" : "Steelheart Inspired",
      "warband" : "Liberators",
      "wounds" : 4
    },
    "targor" : {
      "attack" : {
        "damage" : 1,
        "distance" : 1,
        "name" : "Gore-Axe and Blade",
        "toHit" : 2,
        "toHitIcon" : "SWORDS"
      },
      "defence" : 1,
      "defenceIcon" : "DODGE",
      "inspiration" : "At least three fighters are out of action",
      "move" : 4,
      "name" : "Targor",
      "warband" : "Bloodreavers",
      "wounds" : 2
    },
    "targorinspired" : {
      "attack" : {
        "damage" : 2,
        "distance" : 1,
        "name" : "Gore-Axe and Blade",
        "toHit" : 3,
        "toHitIcon" : "SWORDS"
      },
      "defence" : 1,
      "defenceIcon" : "DODGE",
      "move" : 5,
      "name" : "Targor Inspired",
      "warband" : "Bloodreavers",
      "wounds" : 2
    }
  },
  "warbands" : [ null, {
    "fighters" : [ "garrek", "arnulf", "targor", "saek", "karsus" ],
    "title" : "Bloodreavers"
  }, {
    "fighters" : [ "severin", "angharad", "obryn" ],
    "title" : "Liberators"
  }, {
    "title" : "Sepulchral Guard"
  }, {
    "title" : "Ironskull's Boyz"
  } ]
}
